ocrd_froc/__init__.py
ocrd_froc/charmap.json
ocrd_froc/classmap.py
ocrd_froc/converter.py
ocrd_froc/font_map.json
ocrd_froc/froc.py
ocrd_froc/network.py
ocrd_froc/ocrd-tool.json
ocrd_froc/processor.py
ocrd_froc/cli/__init__.py
ocrd_froc/cli/ocrd_cli.py
ocrd_froc/models/default.froc
ocrd_froc-1.1.0.dist-info/licenses/LICENSE
ocrd_froc-1.1.0.dist-info/METADATA
ocrd_froc-1.1.0.dist-info/WHEEL
ocrd_froc-1.1.0.dist-info/entry_points.txt
ocrd_froc-1.1.0.dist-info/top_level.txt
ocrd_froc-1.1.0.dist-info/RECORD
