Metadata-Version: 2.4
Name: ocrd_froc
Version: 1.1.0
Summary: font recognition and OCR
Author: Guillaume Carriere, Matthias Seuret, Konstantin Baierer
License: Apache-2.0
Project-URL: Repository, https://github.com/OCR-D/ocrd_froc
Requires-Python: >=3.8
License-File: LICENSE
Requires-Dist: ocrd>=3.3.0
Requires-Dist: pandas
Requires-Dist: scikit-image
Requires-Dist: torch>=1.4.0
Requires-Dist: torchvision>=0.5.0
Dynamic: license-file
